LICENSE
MANIFEST.in
README.rst
cyheapq.c
cyheapq.pyx
setup.py
cyheapq.egg-info/PKG-INFO
cyheapq.egg-info/SOURCES.txt
cyheapq.egg-info/dependency_links.txt
cyheapq.egg-info/not-zip-safe
cyheapq.egg-info/requires.txt
cyheapq.egg-info/top_level.txt