Metadata-Version: 1.1
Name: cyheapq
Version: 0.1.1
Summary: Heapq in Cython
Home-page: https://github.com/bndl/cyheapq
Author: Frens Jan Rumph
Author-email: mail@frensjan.nl
License: UNKNOWN
Platform: UNKNOWN
Classifier: Development Status :: 4 - Beta
Classifier: Intended Audience :: Developers
Classifier: Operating System :: OS Independent
Classifier: Programming Language :: Python
Classifier: Programming Language :: Python :: 3.3
Classifier: Programming Language :: Python :: 3.4
Classifier: Programming Language :: Python :: 3.5
Classifier: Programming Language :: Python :: 3.6
